dialogflow/__init__.py
dialogflow_v2/__init__.py
dialogflow_v2/types.py
dialogflow_v2/gapic/__init__.py
dialogflow_v2/gapic/agents_client.py
dialogflow_v2/gapic/agents_client_config.py
dialogflow_v2/gapic/contexts_client.py
dialogflow_v2/gapic/contexts_client_config.py
dialogflow_v2/gapic/entity_types_client.py
dialogflow_v2/gapic/entity_types_client_config.py
dialogflow_v2/gapic/enums.py
dialogflow_v2/gapic/environments_client.py
dialogflow_v2/gapic/environments_client_config.py
dialogflow_v2/gapic/intents_client.py
dialogflow_v2/gapic/intents_client_config.py
dialogflow_v2/gapic/session_entity_types_client.py
dialogflow_v2/gapic/session_entity_types_client_config.py
dialogflow_v2/gapic/sessions_client.py
dialogflow_v2/gapic/sessions_client_config.py
dialogflow_v2/gapic/transports/__init__.py
dialogflow_v2/gapic/transports/agents_grpc_transport.py
dialogflow_v2/gapic/transports/contexts_grpc_transport.py
dialogflow_v2/gapic/transports/entity_types_grpc_transport.py
dialogflow_v2/gapic/transports/environments_grpc_transport.py
dialogflow_v2/gapic/transports/intents_grpc_transport.py
dialogflow_v2/gapic/transports/session_entity_types_grpc_transport.py
dialogflow_v2/gapic/transports/sessions_grpc_transport.py
dialogflow_v2/proto/__init__.py
dialogflow_v2/proto/agent_pb2.py
dialogflow_v2/proto/agent_pb2_grpc.py
dialogflow_v2/proto/audio_config_pb2.py
dialogflow_v2/proto/audio_config_pb2_grpc.py
dialogflow_v2/proto/context_pb2.py
dialogflow_v2/proto/context_pb2_grpc.py
dialogflow_v2/proto/entity_type_pb2.py
dialogflow_v2/proto/entity_type_pb2_grpc.py
dialogflow_v2/proto/environment_pb2.py
dialogflow_v2/proto/environment_pb2_grpc.py
dialogflow_v2/proto/intent_pb2.py
dialogflow_v2/proto/intent_pb2_grpc.py
dialogflow_v2/proto/session_entity_type_pb2.py
dialogflow_v2/proto/session_entity_type_pb2_grpc.py
dialogflow_v2/proto/session_pb2.py
dialogflow_v2/proto/session_pb2_grpc.py
dialogflow_v2/proto/validation_result_pb2.py
dialogflow_v2/proto/validation_result_pb2_grpc.py
dialogflow-2.0.0.dist-info/LICENSE
dialogflow-2.0.0.dist-info/METADATA
dialogflow-2.0.0.dist-info/WHEEL
dialogflow-2.0.0.dist-info/top_level.txt
dialogflow-2.0.0.dist-info/RECORD
